{"files":{"packages/web/dist/assets":{"size":0,"mtime_nanos":0,"mode":0,"is_dir":true},"packages/web/dist/index.html":{"size":490,"mtime_nanos":1782155179239747624,"mode":420,"is_dir":false},"packages/web/dist/assets/index-VFPjDugQ.js":{"size":242217,"mtime_nanos":1782155179239613915,"mode":420,"is_dir":false},"packages/web/dist/assets/index-Bamvg1Z4.css":{"size":25610,"mtime_nanos":1782155179239893917,"mode":420,"is_dir":false},"packages/web/.turbo/turbo-build.log":{"size":1269,"mtime_nanos":1782155179256242586,"mode":420,"is_dir":false},"packages/web/dist/assets/slick-BlzDm7g2.svg":{"size":2152,"mtime_nanos":1782155179239665874,"mode":420,"is_dir":false},"packages/web/dist/assets/ajax-loader-BcnMEykj.gif":{"size":4178,"mtime_nanos":1782155179239853542,"mode":420,"is_dir":false},"packages/web/dist":{"size":0,"mtime_nanos":0,"mode":0,"is_dir":true}},"order":["packages/web/.turbo/turbo-build.log","packages/web/dist","packages/web/dist/assets","packages/web/dist/assets/ajax-loader-BcnMEykj.gif","packages/web/dist/assets/index-Bamvg1Z4.css","packages/web/dist/assets/index-VFPjDugQ.js","packages/web/dist/assets/slick-BlzDm7g2.svg","packages/web/dist/index.html"]}